raiden_contracts/CHANGELOG.md
raiden_contracts/__init__.py
raiden_contracts/constants.py
raiden_contracts/contract_manager.py
raiden_contracts/contract_source_manager.py
raiden_contracts/py.typed
raiden_contracts/data/contracts.json
raiden_contracts/data/deployment_arbitrum-one.json
raiden_contracts/data/deployment_goerli.json
raiden_contracts/data/deployment_goerli_unstable.json
raiden_contracts/data/deployment_rinkeby-arbitrum.json
raiden_contracts/data/deployment_services_arbitrum-one.json
raiden_contracts/data/deployment_services_goerli.json
raiden_contracts/data/deployment_services_goerli_unstable.json
raiden_contracts/data/deployment_services_rinkeby-arbitrum.json
raiden_contracts/data/gas.json
raiden_contracts/data/source/__init__.py
raiden_contracts/data/source/lib/ECVerify.sol
raiden_contracts/data/source/lib/MessageType.sol
raiden_contracts/data/source/raiden/.TokenNetwork.sol.swp
raiden_contracts/data/source/raiden/Controllable.sol
raiden_contracts/data/source/raiden/SecretRegistry.sol
raiden_contracts/data/source/raiden/Token.sol
raiden_contracts/data/source/raiden/TokenNetwork.sol
raiden_contracts/data/source/raiden/TokenNetworkRegistry.sol
raiden_contracts/data/source/raiden/Utils.sol
raiden_contracts/data/source/services/MonitoringService.sol
raiden_contracts/data/source/services/OneToN.sol
raiden_contracts/data/source/services/ServiceRegistry.sol
raiden_contracts/data/source/services/UserDeposit.sol
raiden_contracts/data/source/test/CustomToken.sol
raiden_contracts/data/source/test/HumanStandardToken.sol
raiden_contracts/data/source/test/MonitoringServiceInternalsTest.sol
raiden_contracts/data/source/test/OneToNInternalsTest.sol
raiden_contracts/data/source/test/SignatureVerifyTest.sol
raiden_contracts/data/source/test/StandardToken.sol
raiden_contracts/data/source/test/TokenNetworkInternalsTest.sol
raiden_contracts/data/source/test/UDCTransfer.sol
raiden_contracts/data/source/test/__init__.py
raiden_contracts-0.50.2.dist-info/LICENSE
raiden_contracts-0.50.2.dist-info/METADATA
raiden_contracts-0.50.2.dist-info/WHEEL
raiden_contracts-0.50.2.dist-info/entry_points.txt
raiden_contracts-0.50.2.dist-info/top_level.txt
raiden_contracts-0.50.2.dist-info/RECORD
