Metadata-Version: 2.1
Name: raiden-contracts
Version: 0.50.2
Summary: Raiden contracts library and utilities
Home-page: https://github.com/raiden-network/raiden-contracts/
Author: Brainbot Labs Est.
Author-email: contact@brainbot.li
License: MIT
Keywords: raiden ethereum blockchain
Platform: UNKNOWN
Classifier: Development Status :: 3 - Alpha
Classifier: Intended Audience :: Developers
Classifier: License :: OSI Approved :: MIT License
Classifier: Natural Language :: English
Classifier: Programming Language :: Python :: 3
Classifier: Programming Language :: Python :: 3.8
Classifier: Programming Language :: Python :: 3.9
Requires-Dist: click (>=7.0)
Requires-Dist: coincurve (>=8.0.0)
Requires-Dist: eth-abi (<4.0.0,>=2.0.0)
Requires-Dist: eth-typing (<4.0.0,>=2.2.1)
Requires-Dist: eth-utils (<3.0.0,>=1.8.4)
Requires-Dist: py-solc-x
Requires-Dist: semantic-version (>=2.8)
Requires-Dist: web3 (>=5.28.0)
